han2jamo/__init__.py
han2jamo/__main__.py
han2jamo/han2jamo.py
han2jamo/utils.py
han2jamo-0.0.1a0.dist-info/DESCRIPTION.rst
han2jamo-0.0.1a0.dist-info/METADATA
han2jamo-0.0.1a0.dist-info/RECORD
han2jamo-0.0.1a0.dist-info/WHEEL
han2jamo-0.0.1a0.dist-info/metadata.json
han2jamo-0.0.1a0.dist-info/top_level.txt
