Metadata-Version: 2.0
Name: han2jamo
Version: 0.0.1a0
Summary: Fastest Hangle To Jamo Library
Home-page: https://github.com/codertimo/han2jamo
Author: Junseong Kim
Author-email: codertimo@gmail.com
License: UNKNOWN
Platform: UNKNOWN
Classifier: Programming Language :: Python :: 3
Classifier: License :: OSI Approved :: Apache Software License
Classifier: Operating System :: OS Independent
Requires-Dist: six
Requires-Dist: tqdm
